ken_perlin_noise/__init__.py
ken_perlin_noise-0.0.0.dist-info/METADATA
ken_perlin_noise-0.0.0.dist-info/WHEEL
ken_perlin_noise-0.0.0.dist-info/top_level.txt
ken_perlin_noise-0.0.0.dist-info/RECORD
