Metadata-Version: 2.1
Name: ken-perlin-noise
Version: 0.0.0
Summary: UNKNOWN
Home-page: https://github.com/EgorVoron/py-perlin-noise
Author: EgorVoron
License: MIT
Platform: UNKNOWN
Requires-Python: >=3
Requires-Dist: numpy (>=1.15)
